{"algorithm":"RandomReduction","corpus":"grieg_lyric_pieces","groundTruth":["GM","Am","DMm7","GM","Am","DMm7","GM","Em","Bm","Bm","Bm","Bm","D♯m","D♯m","D♯m","Em","Em","A♯o7","Bm","D♯M","Bm","Bm","Bm","E♯o7","D♯m","C♯Mm7","D♯m","D+","Amm7","AMm7","Amm7","Amm7","AMm7","Dmm7","DMm7","Dmm7","Dmm7","DMm7","GM","Am","DMm7","GM","Am","DMm7","GM","Em","Bm","Bm","Bm","Bm","D♯m","D♯m","D♯m","Em","Em","A♯o7","Bm","D♯M","Bm","Bm","Bm","E♯o7","D♯m","C♯Mm7","D♯m","D+","Amm7","AMm7","Amm7","Amm7","AMm7","Dmm7","DMm7","Dmm7","Dmm7","DMm7","GM","Am","DMm7","GM","Am","DMm7","GM"],"id":"20230420015429_allexps","piece":"op47n06","results":[{"accuracy":0.3614457831325301,"chordLabels":["GM","CM","CM","GM","CM","GM","C♯o","Em","Bm","BM","Bm","Bm","F♯m","F♯M","F♯m","CM","Em","C♯%7","GM","BM","Bm","BM","Bm","Bm","DM","AM","F♯m","F+","CM","AMm7","AMm7","CM","AM","DMm7","F♯o","Dm","Dm","DMm7","GM","CM","DMm7","GM","CM","DM","GM","Em","Bm","GM","Bm","DM","F♯m","AM","F♯M","Em","Em","Em","Bm","Em","DM","Bm","Bm","Bm","DM","Bm","F♯M","F+","CM","AM","Am","AMm7","AMm7","DMm7","DMm7","Dm","FM","F♯m","C♯%7","AM","DMm7","GM","Am","DMm7","GM"],"likelihood":-15.076620276536271,"reruns":1,"runTime":1.073514e-3,"slices":[["D4","B4","B4","G3"],["C5","C5","G3","G3"],["D4","C5","C5","A5","G3","G3"],["D5","D5","B4","B5","B5","G5"],["E5","E5","D4","C5","C5","C5","A5","G3","G3","G3"],["D4","C♯4","A4","F♯6","G3","G3","G3"],["D4","D4","C♯4","C♯4","G3","G3","G3","G6","G5"],["E6","E6","E6","E6","E6","G6","G6"],["D7","D7","D7","B6","B5","F♯6","F♯6"],["B6","F♯5"],["D7","B4","F♯6","F♯6","F♯6","F♯6"],["D6","D6","D6","D6","B6","B6","B5","B5","F♯6"],["C♯6","C♯6","C♯6","A6","A6","F♯6","F♯6","F♯5","F♯5"],["D6","D6","C♯5","C♯5","C♯5","C♯5","C♯5","B6","C♯7","F♯6"],["C♯6","C♯6","C♯6","A6","A6","A6","F♯4","F♯4","F♯4","F♯4"],["E5","G5"],["E6","B4","B4","G5"],["C♯5","C♯5","C♯5","B5","B5","G5"],["D6","B4","B4","G5","G5"],["E6","E6","C♯5","B5","B5","F♯4","F♯4","F♯4"],["D6","B5","F♯5","F♯4","F♯4"],["B4","B4","B4","B4","F♯5"],["D5","D5","B5","B5","B5","F♯4"],["D5","G♯4","F♯5","F♯4","F♯4"],["D5","D5","A5","A5","A5","A5","A5","A4","A4","F♯5","F♯4","F♯4"],["D5","C♯4","C♯6"],["C♯4","C♯4","C♯4","C♯5","C♯5","C♯5","A5","F♯3","F♯3"],["F3","F3","C♯4","C♯4","C♯4","C♯4","C♯4","C♯5","C♯5","C♯5","A5"],["E3","E4","E4","E4","C5","C6","G5","G5"],["E3","E3","E3","E3","E3","A3","G5"],["E3","C5","A3","A3","G5","G5"],["E3","E3","C5"],["E3","C♯5","C♯5","A3"],["D6","D6","D4","C6"],["C6","C6","C6","A3","F♯5","F♯5"],["D6","D4","F5","F5","F5","F5","F6","A3","A4"],["D4","D4","D4","D4","E6","F5"],["D3","C6","F♯6","F♯5","F♯5"],["D4","D4","C♯4","B6","B6","B5","G6","G6"],["C7","C6","A6","G3","G4"],["D4","C6"],["D5","D5","D5","D5","B5","B5","G3","G6"],["E6","C♯5","C6","C6","C6","C6","C6","C6","C6"],["D5","A5","A5","A5","A5","F♯6","G4"],["D5","B5","G7","G4","G4"],["E6","E6","E6","B6","G6","G6","G6","G6","G6"],["D7","B5","B5","B5","B5","F♯6","F♯6","F♯6","F♯6","F♯6"],["F♯5","G6","G6","G6","F♯7"],["D7","B4","F♯6","F♯5"],["D6","F♯6"],["C♯6","C♯6","C♯6","C♯6","A6","F♯6","F♯6","F♯6","F♯5","F♯5"],["D6","C♯5","B6","C♯7"],["C♯6","C♯6","C♯6","F♯6","F♯4","F♯4"],["E5","E5","E5","E5","E5","B5","G5"],["E6","B4","B4","B4","B4","G5"],["C♯5","B4","G5"],["D6","D6","D5","B4","B5"],["E6","E6","F♯4","G5","G5"],["D6","D6","F♯4","F♯4","F♯4"],["D5","B4","B4","B4","F♯5","F♯5"],["D5","B5","B5","B5","B5","B5","B5","F♯4","F♯4"],["D5","D5","D5","G♯4","F♯5","F♯4","F♯4"],["D5","A5","A4"],["D5","D5","C♯4","G♯4","F♯5"],["C♯4","C♯5","C♯5","F♯3"],["F3","F3","C♯4","C♯4","C♯4","C♯5","A5","A5","A5","A5"],["E4","E4","E4","C5","C5","C6"],["E3","C♯5","A5","A5","A2","A2","A3","A3","G5"],["E3","E4","C5","A3"],["E4","E4","A3","A3","A3","G5","G5"],["A3","G5","G5","G5"],["D4","C6","A3","A4","A4","A4"],["D4","C6","A3","A3","F♯5","F♯5","F♯5","F♯5"],["D6","D6","D6","D4","F5","C6","A4","A4","A4"],["F5","F5","F5","F5","A3","A3"],["A3","F♯6","F♯5","F♯5"],["D6","C♯4","C♯5","B6","G6","G6","G4"],["E6","C♯4","C♯5","C7","C6","A6"],["D5","D4","C♯4","C♯4","C6","A5","A5","A6","F♯6"],["D5","D4","D4","C♯5","B5","G3","G6","G6","G4"],["C6","C6","C6","C6","C6","A6","A6","G4"],["D5","C6","C6","A5"],["D5","D5","B4","B5","G6","G5","G5"]]},{"accuracy":0.3855421686746988,"chordLabels":["GM","CM","DMm7","GM","CM","DMm7","GM","Em","Bm","F♯Mm7","BM","Bm","F♯M","DM","F♯m","EM","Em","BM","GM","C♯o","F♯M","Bm","Bm","Bm","DM","G♯%7","F♯m","FM","CM","AMm7","Em","AMm7","AMm7","Dmm7","DMm7","Dm","Dm","DM","GM","Am","DMm7","GM","AM","DM","GM","Em","Bm","GM","DM","Bm","AM","Bm","F♯m","Em","EM","C♯%7","Bm","C♯o","F♯M","Bm","DM","BM","F♯m","C♯Mm7","F♯m","FM","Am","AMm7","Am","Am","AMm7","Am","DM","FM","FM","DMm7","Em","CM","DMm7","Bm","CM","F♯o","GM"],"likelihood":-14.994732252740828,"reruns":1,"runTime":5.97916e-4,"slices":[["D5","D4","D4","D4","B5","G3","G5"],["D4","C5","G3"],["D4","D4","D4","D4","D4","C5","A5","F♯5"],["D5","B4","B5","G3","G3","G3","G5"],["E5","D4","D4","D4","C5","C5","C5","C5","G3"],["D4","C5","A4","F♯6","F♯5"],["D5","D4","D4","B5","G3","G5","G5"],["E7","E7","E7","E6","B6","B6","G6"],["D7","B6","B5","B5","B5","F♯6","F♯6","F♯6"],["E7","E7","E7","B6","F♯5","F♯5","F♯7"],["B6","B4","F♯6","F♯6"],["D6","D6","D6","B6","B6","B6","B5","B5","B5"],["C♯6","F♯5","F♯5","F♯5","F♯5"],["D6","D6","C♯5"],["C♯5","C♯5","C♯5","C♯6","A6","F♯6","F♯4"],["E5","E5","E5","B5"],["E6","E6","B4","B4","B4","B4","B4","G5","G5","G5","G5"],["C♯5","B4","B4","B5","B5"],["D6","D5","G5","G5","G5"],["C♯5","C♯5","F♯4","F♯4","G5","G5"],["F♯5","F♯5"],["D5","B4","B4","B4","B4","F♯5"],["D5","B5","B5","F♯4","F♯4"],["D5","D5","D5","G♯4","F♯5","F♯4","F♯4"],["D5","D5","F♯5","F♯5","F♯4","F♯4"],["D5","C♯4","B5","G♯4","G♯4","G♯4","F♯5","F♯5","F♯5"],["C♯4","C♯4","C♯4","A5","F♯3","F♯3","F♯3"],["F3","F3","C♯5","A5","A5"],["C5","C5","C6","A3","G5"],["E3","C♯6","A5","A2","A2","G5"],["E3","E4","G5","G5"],["E3","E3","E4","E4","A3","G5"],["E3","E3","C♯5","C♯6","A5","A3","A3","G5","G5"],["D4","D4","F5","F5","F5","C6","C6","A3","A3"],["D4","D3","C6","A3","F♯6","F♯6","F♯5","F♯5"],["D4","D4","F5","A3","A4","A4","A4","A4","A4"],["D4","D4","E6","F5","A3","A4"],["D4","D3","A3","A3","A3","A3","F♯5"],["D6","D5","D4","B6"],["C♯4","C7","C7","C6","C6","A6"],["D5","D4","D4","D4","C♯4","C6","C6","A6","A6","A6","F♯6","G4"],["D4","C♯5","B5","G3","G6","G4","G4"],["C♯5","A6","A6","A6","A6"],["D5","C♯5","C6","A5","A6","A6","A6","F♯6","G4","F♯7","F♯7","F♯7"],["D5","B6","G7"],["E6","E6","G6"],["D7","B6","B6","B5","B5","F♯6","F♯6"],["F♯5","F♯5","G6","G6","G6","G6"],["D7","D7","F♯6","F♯6","F♯6","F♯6","F♯6","F♯5"],["D6","D6","B6","B5","B5","B5","F♯6"],["C♯6","C♯6","C♯6","A6","A6"],["D6","D6","C♯5","B6"],["C♯5","C♯5","C♯6","A6","A6","A6","A6","F♯4"],["E5","E5","B5","G5","G5"],["E6","B4","B4","B4","B4","B4","B4","B4","B4"],["C♯5","C♯5","B4","B5","G5"],["D6","D5","D5","B4","B4","B4","B4","B5"],["E6","C♯5","F♯4","G5"],["F♯5","F♯5","F♯4","F♯4","F♯4","F♯4"],["D5","B4","F♯5","F♯5"],["D5","D5","F♯4","F♯4","F♯4"],["B5","B5","G♯4","F♯5","F♯4"],["A4","A4","F♯5","F♯4"],["C♯4","C♯4","B5","G♯4"],["C♯4","C♯5","C♯5","A5","F♯3","F♯3"],["F3","F3","C♯5","A5"],["E3","E3","E4","E4","C6","A3","G5"],["C♯5","C♯5","C♯5","C♯6","A2","G5"],["E3","C5","C6","A3","A3","A3","G5"],["E3","E4","C5","C5","B5","B5","A3"],["E3","C♯6","A5","A2","G5","G5"],["C6","C6","A3","A4"],["D6","D4","D3","C6","A3","A3","A3","F♯6","F♯6","F♯5","F♯5"],["F6","F6","A3","A4","A4","A4","A4"],["D4","F5","C6","C6","A4"],["D3","D3","C6"],["C♯4","B6","G6","G4"],["D5","E6","C7","G4"],["D5","C6","C6","C6","C6","A5","F♯6","F♯6","F♯6"],["D7","C♯5","B6","B5","B5","B5","B5"],["D♯5","E6","C7","C6","C6","C6","A6","G4"],["D5","C♯5","C6","C6","A5","A5","F♯6","F♯6","G4","G4"],["B5","G5","G5"]]},{"accuracy":0.3614457831325301,"chordLabels":["GM","CM","GM","GM","AMm7","F♯m","GM","Em","Bm","Em","BM","Bm","F♯m","AM","C♯M","Em","EM","C♯%7","Bm","C♯m","Bm","Bm","BM","G♯%7","DM","C♯Mm7","F♯M","C♯M","CM","AM","CM","EM","AM","Dm","DMm7","DM","DM","DMm7","GM","CM","AMm7","GM","CM","F♯o","GM","Em","BM","Em","Bm","Bm","F♯M","Bm","F♯m","Em","Em","Em","Bm","F♯M","DM","Bm","Bm","G♯%7","DM","C♯M","F♯m","F+","CM","AM","AMm7","AMm7","AM","FM","DMm7","Dm","FM","DMm7","GM","AM","DMm7","Bm","D♯o7","DMm7","GM"],"likelihood":-14.72369682238504,"reruns":1,"runTime":4.8471399999999997e-4,"slices":[["D4","B4","G3"],["D4","C5","C5","C5","C5","C6","C6","C6","A5","G3"],["D4","A5","F♯5","G3","G3","G3"],["D5","D4","D4","D4","B4","B5","G5"],["A5","G3","G3"],["C♯4","A5","A4","F♯6","F♯5","G3"],["D4","B4","B4","B4","B4","B5","G6","G5","G5"],["E7","E7","E6","B6","G6"],["D7","D7","D7","D7","B6","B5","B5","F♯6","F♯6"],["E7","F♯5","G6","G6"],["B6","F♯6","F♯6","F♯6","F♯5"],["D6","D6","D6","B6","B6","B6","B6","B5","B5","F♯6"],["C♯6","C♯6","C♯6","C♯6","A6","A6","F♯6","F♯5","F♯5","F♯5","F♯5"],["D6","C♯5","C♯5","B6","C♯7"],["C♯5","C♯6"],["E5","E5","E5","G5","G5"],["E6","B4","B4","B4"],["E6","C♯5","C♯5","B4","G5"],["D6","D6","B4","B5"],["E6","C♯5","C♯5","C♯5","C♯5","B5","F♯4"],["D6","B3","F♯5","F♯5","F♯4","F♯4"],["D5","D5","B4","B4","B4","B4","F♯5","F♯5","F♯5"],["B5","F♯4","F♯4","F♯4","F♯4"],["D5","D5","D5","B5","G♯4","G♯4","G♯4","F♯4","F♯4"],["D5","A5","A5","A4","F♯5","F♯4","F♯4"],["C♯4","B5","B5","B5","G♯4","G♯4","G♯4"],["C♯4","C♯5","C♯5","F♯5","F♯3","F♯3","F♯3"],["F3","C♯4","C♯4","C♯5","C♯5","C♯5"],["E3","E3","E4","E4","C6","G5","G5"],["E3","E3","C♯5","C♯5","C♯6","C♯6","A2","A2","A2","A2","A2","A3"],["E4","G5"],["E3","E3","E4","C5","B5","B5","A3"],["E3","E3","A3"],["D4","D4","D4","D4","F5","F5","A4","A4"],["D6","D4","C6","A3","F♯5","F♯5"],["D6","D6","D4","A3"],["D4","D4","E6","A3","A3","A4"],["D4","D4","D3","C6","A3","A3","F♯6"],["D6","D5","D4","C♯4","B6","B5","B5","G6","G6"],["D5","D5","E6","C♯4","C♯5","C7","C6","G4"],["A5","A6","G3"],["D6","C♯4","B5","G6","G6","G6"],["E6","E6","C7","C6","G4"],["C6","A5","A6","F♯6","F♯7"],["B6","B6","B5","G6","G7"],["E6","E6","E6","G6","G6","G6"],["B6","B5","F♯6","F♯6"],["E7","B6","F♯5","F♯5","G6","G6"],["D7","D7","D7","B4","F♯6","F♯6","F♯6","F♯6","F♯6","F♯5"],["D6","B5","B5","F♯6","F♯6"],["C♯6","C♯6","C♯6","F♯5"],["D6","C♯5","B6","B6","B6"],["A6","A6","A6","F♯6","F♯6","F♯4","F♯4","F♯4"],["E5","E5","E5","E5","E5","E5","B5","G5"],["E6","B4","G5","G5","G5"],["E6","E6","C♯5","B4","G5"],["D6","D5","D5","B4","B4","B4","B4","B4"],["E6","C♯5","B5","F♯4","F♯4","F♯4","F♯4"],["D6","D6","D6","F♯5"],["D5","D5","B4","F♯5","F♯5"],["D5","D5","D5","D5","D5","D5","B5","B5","F♯4","F♯4","F♯4"],["D5","D5","D5","G♯4","G♯4","F♯5","F♯4"],["D5","A5","A4","A4","A4","A4","F♯5"],["C♯4","C♯4","G♯4"],["C♯5","A5","F♯5","F♯3"],["F3","F3","C♯4","C♯4","C♯5","C♯5","C♯5","C♯5","A5","A5","A5"],["E3","E3","E3","C5","C6","C6","A3","G5"],["C♯5","C♯5","A3"],["E3","A3","G5","G5"],["E3","A3","G5","G5"],["C♯5","C♯5","C♯5","C♯6","A5","A2","A3"],["F6","C6","C6"],["D4","C6","F♯5"],["D6","D6","D4","F5","A3","A3","A4"],["D4","F5","C6","C6","A3","A3","A3"],["D6","D3","C6","A3","F♯5"],["D6","C♯5","B6","B6","B5","G3"],["D4","C♯4","C7","A6","G3"],["D4","C6","A5","A5","A5"],["D7","B6","B5"],["D♯5","D♯5","C5","C5","C7","C6","C6","C6","C6"],["D5","C6","C6","C6","A5","F♯6","F♯6"],["D4","B5","B5","G5","G5","G5"]]},{"accuracy":0.27710843373493976,"chordLabels":["GM","CM","GM","GM","AMm7","AMm7","GM","Em","Bm","Em","DM","Bm","F♯M","Bm","F♯m","EM","BM","Em","GM","C♯o","Bm","BM","Bm","G♯%7","DM","G♯%7","F♯m","F+","GM","AMm7","Am","Am","AM","DMm7","DM","Dm","Dm","DM","GM","CM","DM","GM","DMm7","DMm7","GM","Em","F♯M","Em","BM","Bm","F♯m","Bm","F♯m","Em","Em","Em","GM","C♯o","DM","Bm","BM","G♯o","DM","F♯M","F♯M","F+","CM","AMm7","Am","Am","C♯m","Dm","DMm7","Dm","DMm7","F♯o","Bm","AM","DM","GM","CM","DMm7","GM"],"likelihood":-14.657559699055268,"reruns":1,"runTime":4.73667e-4,"slices":[["D4","D4","D4","B4","B4","B5","G5","G5"],["E5","D4","C5","C6","G3"],["D4","A5","G3","G3"],["D5","D5","D4","B4","G3"],["E5","C♯4","C♯4","A5","A5","G3","G3"],["C♯4","A5","A5","G3"],["D4","D4","B4","G3","G3","G5","G5","G5"],["E6","E6","E6","G6","G6"],["D7","D7","B5","B5","F♯6"],["E7","E7","E7","F♯5","F♯5","F♯5","G6","G6","G6","F♯7"],["D7","D7","F♯5"],["D6","D6","D6","B6","F♯6"],["C♯6","C♯6","F♯5"],["D6","D6","C♯5","C♯5","C♯5","B6","F♯6"],["C♯6","C♯6","C♯6","A6","F♯4"],["E5","E5","E5","E5"],["B4","B4"],["E6","B4","G5","G5","G5"],["D6","D5","D5","D5","B4","G5","G5"],["E6","C♯5","C♯5","F♯4","F♯4","G5","G5","G5"],["D6","B5","B3","B3","F♯4","F♯4","F♯4"],["B4","B4","B4","B4","B4","F♯5","F♯5","F♯5"],["D5","B5","B5","F♯4"],["D5","G♯4","G♯4","F♯5","F♯5","F♯4","F♯4","F♯4"],["D5","A5","F♯4","F♯4"],["D5","G♯4","G♯4","F♯5"],["C♯4","C♯4","C♯4","C♯5","C♯5","C♯5","C♯5","C♯5","A5","A5","A5","A5","F♯3","F♯3"],["F3","F3","C♯5","C♯5","C♯5","A5","A5","A5","A5"],["G5","G5"],["E3","A3","G5","G5","G5","G5"],["E3","E3","E3","E4","E4","C5","C5","C5","C6","A5","A3"],["E3","E4","E4","E4","C5","C5","A3","A3"],["E3","C♯5","A3"],["D6","D4","D4","C6","A3"],["D4","D4","D3","A3","F♯6","F♯5"],["D6","D4","F5","F5","F6","C6"],["D4","E6","E6","F5","F5","A3"],["D4","D3","F♯5"],["D6","D6","D4","C♯4","B5","G3"],["C7","C6","A6","G3","G3"],["A6","A6","F♯6","G4"],["D5","D5","B5","B5","G6","G4","G4","G4","G4"],["D5","D5","C7"],["D5","C6","F♯6"],["D5","G4"],["E7","E6","E6","B6","G6","G6"],["F♯6","F♯6"],["E7","E7","F♯5","F♯5","G6","G6"],["B6","B4","F♯6","F♯6"],["D6","B6","B5","B5","B5","B5","F♯6","F♯6"],["A6","A6","A6","F♯6","F♯6","F♯5","F♯5","F♯5","F♯5"],["D6","D6","C♯5","B6","C♯7","F♯6"],["A6","A6","F♯4","F♯4","F♯4"],["E5","E5","E5","B5","B5","G5","G5"],["E6","E6","B4","B4","G5","G5"],["C♯5","B4","B4","B5","G5"],["D6","D5","D5","D5","D5","D5","G5","G5"],["E6","C♯5","C♯5","C♯5","C♯5","F♯6","F♯4","F♯4","G5","G5","G5","G5"],["D6","F♯5","F♯5","F♯5","F♯4","F♯4"],["D5","D5","D5","B4","B4"],["B5","F♯4","F♯4","F♯4","F♯4","F♯4","F♯4","F♯4"],["D5","D5","D5","D5","B5","B5","G♯4"],["D5","A4","F♯4","F♯4"],["D5","C♯4","C♯4","G♯4","F♯5"],["C♯4","C♯4","C♯4","C♯5","F♯5","F♯5","F♯3"],["F3","F3","C♯4","C♯4","C♯4","C♯4","A5","A5"],["E3","E3","E3","E4","E4","C5","C5","C5","G5","G5","G5"],["C♯5","A5","A3","A3","G5"],["E4","C5","B5","A5","A3","A3"],["E4","C5","B5","B5","A3","A3"],["E3","C♯5","C♯5"],["D6","D6","D6","D4","F5","F6","C6","A3"],["D4","C6","C6","A3","F♯5"],["D6","D4","F5","F5","F5","F6","A4"],["D4","C6","A3"],["C6","A3","A3","F♯6"],["D5","D4","C♯4","C♯5","B6","B5","G6"],["D4","C♯4","C6","A6","A6","G4"],["D5","C♯5","A6","A6","F♯6","G3"],["D6","G3","G6","G6","G4","G4"],["E6","C6"],["D5","D5","C6","F♯6"],["D5","D4","D4","D4","B4","B4","G3","G5"]]},{"accuracy":0.2891566265060241,"chordLabels":["GM","CM","DM","GM","GM","DM","GM","Em","Bm","Em","Bm","DM","F♯M","F♯M","F♯m","EM","EM","Em","GM","Em","BM","Bm","Bm","G♯%7","DM","Bm","F♯M","F+","Am","AMm7","AMm7","Am","AM","DMm7","DMm7","DMm7","CM","DMm7","GM","CM","DM","GM","CM","F♯m","GM","EM","DM","GM","Bm","Bm","F♯m","DM","F♯m","Em","GM","Em","GM","F♯M","Bm","Bm","Bm","DM","DM","G♯o","F♯M","F+","Am","AM","AMm7","EM","AMm7","Dm","DM","Dm","DM","F♯o","GM","AM","F♯o","GM","Am","F♯o","Em"],"likelihood":-15.124311191238743,"reruns":1,"runTime":9.0428044e-2,"slices":[["D5","G3","G3"],["E5","E5","E5","C6","C6","C6"],["D4","D4","D4","D4","D4","C5","A5","A4","F♯5","G3"],["D4","B4"],["D4","D4","C5","A5","G3"],["D4","D4","D4","C5","A4","A4","A4","G3","G3"],["D5","D4","D4","B4","G6"],["E7","E7","E6","B6","G6","G6","G6","G6","G6","G6","G6"],["D7","B5","B5","B5","B5","F♯6","F♯6","F♯6","F♯6"],["E7","E7","F♯5","G6","G6","G6","F♯7","F♯7"],["D7","B6","B4","B4"],["D6","D6","D6","D6","D6","F♯6"],["C♯6","C♯6","C♯6","F♯5"],["C♯5","C♯5","C♯5","C♯7","F♯6"],["A6","F♯4","F♯4","F♯4"],["E5","E5","E5","E5","E5"],["E6","E6","E6","E6","B4","B4"],["C♯5","B4","B4","B5","B5","G5"],["D5","B4","G5","G5","G5","G5"],["E6","E6","C♯5","F♯4","F♯4","G5","G5"],["B3","B3","F♯5","F♯4","F♯4"],["D5","D5","D5","B4","B4","B4","B4","F♯5","F♯5"],["D5","D5","B5","F♯4","F♯4"],["D5","B5","G♯4","G♯4","F♯5","F♯4","F♯4"],["D5","A4"],["D5","C♯4","B5","G♯4","F♯5"],["C♯5","C♯5","F♯5","F♯3"],["F3","F3","F3","C♯4","C♯4","C♯4","A5"],["C5","C5","C6","A5","A3","A3"],["E3","E3","C♯5","A2","A3","G5","G5","G5"],["E3","A5","A3","A3","G5"],["E3","E3","E3","E3","C5","C5","C5","B5","B5","B5","A3","A3"],["E3","C♯5","C♯6","C♯6","A2"],["D4","D4","C6","A3","A3","A3","A4","A4"],["D4","D4","C6","F♯6","F♯5"],["D4","D4","E6","C6","A3","A3","A3","A3","A4","A4"],["E6","E6","F5"],["D4","D4","D3","C6","C6","C6","C6","A3"],["D6","G3","G6"],["E6","E6","C♯5","C6","G4"],["A6","F♯6","G3"],["D6","C♯5","B6","G6","G4"],["E7","E7","C6","C6","C6","A6","G4"],["C♯5","A5","A5","A6","A6","F♯7"],["B6","G6","G7","G4","G4","G4"],["E7","E6","B6","B6"],["D7","F♯6","F♯6"],["F♯5","F♯5","G6","G6"],["D7","B4","B4","B4","B4","F♯6","F♯6"],["D6","D6","B6","B6"],["C♯6","C♯6","C♯6","C♯6","A6","A6","F♯5","F♯5","F♯5"],["D6","D6","C♯5"],["C♯5","A6","A6","F♯6","F♯4"],["E5","E5","E5","E5","G5"],["B4","B4","B4","B4","B4","B4","B4","G5","G5"],["E6","E6","C♯5","B4","B4","B4","B4","G5"],["D6","D5","D5","B4","B5","G5"],["C♯5","B5","F♯6","F♯4","F♯4","F♯4"],["D6","D6","B5","B3","F♯5","F♯5","F♯4","F♯4"],["D5","D5","D5","D5","D5","B4","F♯5","F♯5"],["D5","B5","B5","B5","F♯4","F♯4"],["D5","F♯5","F♯5","F♯4","F♯4"],["A5","A4","A4","F♯4"],["D5","D5","C♯6","C♯6","B5","B5","B5","G♯4","G♯4","G♯4"],["C♯5","C♯5","F♯3","F♯3"],["F3","F3","F3","C♯4","C♯5","C♯5","C♯5","C♯5"],["E4","E4","C5","C5","C6","C6","A3","A3"],["C♯5","C♯5","A3"],["E3","E4","E4","C5","A5","A3","A3","G5","G5"],["E3","E4","E4","B5","A3"],["E3","C♯5","A2","A2","A3","A3","G5"],["D6","D4","D4","F5","F5","F6","C6"],["D4","C6","A3","A3","F♯6","F♯5","F♯5","F♯5","F♯5"],["D6","D4","D4","E6","F5","A3","A4","A4","A4"],["D4","A3"],["C6","C6","A3","F♯6","F♯5"],["D6","B6","G6"],["E6","E6","C♯5","C♯5","C♯5","C7","C6"],["C♯4","C6","F♯6","F♯6","G3"],["D6","D5","B6","B5","G3","G6"],["D♯5","E6","E6","C7","C6","A6","A6","A6","G4"],["C♯5","C6","A6","A6","F♯6","G4","F♯7"],["C♯5","B4","B4","B4","B5","B5","G3","G6","G5"]]}]}