{"algorithm":"RandomSample","corpus":"grieg_lyric_pieces","groundTruth":["AM","E♯Mm7","E♯Mm7","E♯Mm7","E♯Mm7","E♯m","EMm7","EMm7","EMm7","EMm7","B%7","EM","C♯m","EM","B♯M","AM","AM","AM","E♯Mm7","E♯Mm7","E♯Mm7","E♯Mm7","E♯m","EMm7","EMm7","EMm7","EMm7","B%7","EM","EMm7","Am","EMm7","AMm7","C♯♯Mm7","B♯M","F♯%7","EM","C♯m","EM","B♯M","AM","B%7","AM","B%7","AM"],"id":"20230420015256_allexps","piece":"op62n05","results":[{"accuracy":2.2222222222222223e-2,"chordLabels":["DM","D♭Mm7","G♭M","CM","G♭M","F♯o7","EIt","FM","B♭M","EM","BM","Do7","C♯Mm7","C♭M","Bm","F♯o","Do","AM","DM","A♭m","DM","B♭Mm7","Dm","E♭Mm7","FM","DM","DM","EMm7","G♭M","DMm7","C♭M","A♭M","AM","Do7","A♭M","B♭M","D♭Mm7","AM","C♭M","Ao7","GM","B♭M","CM","FM","E♭M"],"likelihood":-15.13676582274135,"reruns":1,"runTime":1.528e-4,"slices":[["D3","D3","A♭-7","G♭-10","F♯9"],["C♭-11","F-2"],["G♭-10","G♭-10","G1"],["C♭-11","B7","C0","G1","F-2"],["G♭-10","B♭-4","F♯9"],["C♭-11","C0","C♯11","F♯9"],["G♭-10","B7","B♭-4","C♯11","E♭-5"],["E6","D♭-8","A4","E♭-5"],["D3","F-2"],["E6","E6"],["B7","C♯11","D♭-8","E♭-5","F♯9"],["C♭-11","A4"],["B7","C♯11"],["C♭-11","E♭-5"],["D3","E6","B7","F♯9","F-2"],["C0","A4","A4","F♯9"],["D3","D3","A♭-7","E♭-5","F-2"],["B7","C♯11","A4","F-2"],["D3","F♯9"],["A♭-7","E6","C♭-11"],["F♯9","F-2"],["A♭-7","D3","B♭-4","B♭-4"],["D3","E6","F-2"],["D♭-8","G1"],["C0","D♭-8","A4","E♭-5","F-2"],["D3","B♭-4","F♯9"],["D3","A4"],["D3","E6"],["C♭-11","B♭-4","D♭-8"],["A♭-7","A4","F♯9"],["G♭-10","C♭-11"],["A♭-7","G1"],["E6","C0","C♯11"],["C♭-11","F♯9"],["C♭-11","C0"],["B♭-4","F♯9","F-2"],["C♭-11","C♭-11","D♭-8","F♯9"],["D3","B7","C0","C♯11"],["G♭-10","G♭-10","C♭-11","F♯9"],["G♭-10","C♭-11","C♯11"],["D3","G♭-10","B7","G1"],["D3","B7","B♭-4","C0","F-2"],["A♭-7","E6"],["A♭-7","E6","B♭-4","A4"],["D3","A♭-7","E♭-5"]]},{"accuracy":2.2222222222222223e-2,"chordLabels":["CM","DMm7","Do7","E♭M","F♯m","Bo7","D♭Mm7","GM","A♭M","C♯Mm7","F♯M","GM","CM","DM","D♭M","D♭M","AM","F♯M","F♯M","D♭M","F♯o7","CM","E♭Mm7","BMm7","Ao7","DMm7","E♭Mm7","C♭M","FM","CM","CMm7","DM","Eo7","FMm7","FM","B♭Mm7","DMm7","Cm","DM","D♭Mm7","Eo7","BGer","B♭M","D♭M","B♭M"],"likelihood":-15.302516937787777,"reruns":1,"runTime":4.4627e-5,"slices":[["A♭-7","E6"],["G♭-10","C0","F♯9"],["C♭-11","A4"],["B♭-4","E♭-5","E♭-5"],["C♯11","A4","D♭-8","F♯9"],["A♭-7","A♭-7","F♯9"],["C♭-11","C♭-11","C♯11","F-2","F-2"],["B7","C0","G1","F♯9"],["A♭-7","C♯11","E♭-5","G1"],["A♭-7","B7","B7","C♯11"],["G♭-10","F♯9","F♯9"],["C♭-11","B7"],["E6","C♭-11"],["D3","C0","A4","G1","F♯9"],["C0","D♭-8","D♭-8","F♯9"],["A♭-7","F-2"],["B7","C♯11","A4"],["F♯9","F♯9"],["A♭-7","C♯11","F♯9"],["A♭-7","A♭-7","G♭-10","C0","D♭-8"],["C♭-11","B♭-4","C♯11","E♭-5","F♯9"],["B7","C♯11","E♭-5","G1","F-2"],["D♭-8","G1"],["G♭-10","B7","C♯11","D♭-8","A4"],["G♭-10","C0","A4"],["D3","C0","C0"],["B7","D♭-8","E♭-5"],["G♭-10","C♭-11","C♭-11"],["E6","G1","F-2","F-2"],["D3","E6","C0"],["E6","B♭-4"],["A4","F♯9"],["E6","C♯11","D♭-8","D♭-8"],["D3","A♭-7","C0","A4","E♭-5"],["C0","C0","A4","F-2"],["A♭-7","E6","B♭-4","F♯9"],["D3","C0","A4","A4"],["A4","G1","E♭-5"],["G♭-10","A4","F♯9","F♯9"],["C♭-11","C♯11","F-2"],["D3","E6","D♭-8"],["B7","B7","C♭-11","D♭-8"],["D3","G♭-10","F-2"],["A♭-7","D♭-8","D♭-8","E♭-5","F♯9"],["D3","C♭-11","B♭-4"]]},{"accuracy":2.2222222222222223e-2,"chordLabels":["B♭Mm7","DM","BGer","B♭M","DM","A♭M","GMm7","D♭M","Bo7","AM","E♭M","AM","Ao7","C♭M","CMm7","DMm7","D♭M","CM","DMm7","F♯o7","C♭M","C♭M","Em","FMm7","E♭M","DM","F♯M","FM","D♭M","CM","C♯o7","AM","A♭Mm7","Fo","D♭M","Do","Fo","Am","FM","C♯o7","Fm","E♭M","AM","C♭M","AMm7"],"likelihood":-15.325868319235209,"reruns":1,"runTime":4.0722e-5,"slices":[["A♭-7","B♭-4"],["D3","C♯11","A4","F-2"],["A♭-7","B7","C♭-11","D♭-8","F♯9"],["B♭-4","G1","F-2","F-2"],["D3","G♭-10","F♯9"],["C0","E♭-5"],["G1","F-2"],["C0","D♭-8","F-2"],["A♭-7","B7","F♯9"],["A♭-7","E6","C♯11","D♭-8"],["B♭-4","G1"],["A♭-7","A♭-7","E6","C♯11","C♯11"],["G♭-10","A4"],["G♭-10","C♭-11","E♭-5","E♭-5","F-2"],["E6","G♭-10","G1"],["D3","C0"],["C0","D♭-8","F-2"],["D3","E6","E6","C♭-11","F-2"],["D3","D3","E6","C0","C♯11"],["C♭-11","G1","E♭-5","F♯9","F♯9"],["G♭-10","C♭-11","C♭-11","B7"],["G♭-10","C♭-11","A4","D♭-8","E♭-5"],["E6","B7","B♭-4","A4","G1"],["C0","E♭-5","F-2"],["C♭-11","G1","G1"],["A4","G1","F♯9","F♯9"],["G♭-10","C♯11","C♯11"],["A♭-7","E6","A4","D♭-8","F-2"],["C0","D♭-8"],["E6","B7","E♭-5","F-2"],["E6","B7","B♭-4","C♯11","E♭-5"],["A♭-7","C♯11","C♯11"],["A♭-7","D3","G♭-10"],["A♭-7","G♭-10","E6","C♭-11","F-2"],["A♭-7","D♭-8","F♯9"],["D3","D3","A♭-7","F-2","F-2"],["D3","G♭-10","C♭-11","C0","F-2"],["E6","A4","E♭-5"],["F-2","F-2"],["G♭-10","B♭-4","C♯11"],["A♭-7","G1","F-2"],["G♭-10","G1"],["E6","C♯11"],["G♭-10","E6","C♭-11","C♭-11"],["C♭-11","A4","G1"]]},{"accuracy":0,"chordLabels":["C♭M","B♭Mm7","AMm7","C♭M","E♭m","Eo7","FM","E♭M","Bo","AMm7","AMm7","DM","C♯M","CM","C♭M","F♯o7","FM","Do","FMm7","G♭M","D♭Mm7","F♯m","EGer","Am","Ao7","B♭M","CM","F♯Mm7","Do7","CMm7","AM","E♭M","FM","Co","AM","Do7","B♭Mm7","AMm7","B♭M","A♭M","GM","AM","E♭M","Do7","GM"],"likelihood":-14.906209611614576,"reruns":1,"runTime":4.0125e-5,"slices":[["C♭-11","D♭-8","E♭-5"],["A♭-7","A♭-7","B♭-4","B♭-4","G1"],["A4","G1"],["G♭-10","C♭-11","C♭-11","C0","F♯9"],["G♭-10","B♭-4","B♭-4","E♭-5","F♯9"],["E6","D♭-8"],["A♭-7","C0","A4"],["E6","C♭-11","B♭-4","B♭-4","B♭-4"],["B7","C0","F♯9","F-2","F-2"],["G♭-10","C♯11","A4","A4","G1"],["A4","G1"],["G♭-10","A4","G1","F♯9","F-2"],["C♯11","C♯11"],["E6","C0","C0"],["G♭-10","G♭-10","C♭-11","C♭-11","F-2"],["A♭-7","E6","C♭-11","F♯9","F♯9"],["E6","C0","C0","B♭-4","F-2"],["A♭-7","A♭-7","D3","D3","F-2"],["E6","C♭-11","E♭-5","F-2"],["G♭-10","A4","D♭-8"],["A♭-7","C♭-11","C♯11","D♭-8"],["C♯11","A4","F♯9"],["G♭-10","G♭-10","E6","E6"],["E6","B7","A4","E♭-5"],["G♭-10","C♭-11","C♯11","A4","E♭-5"],["D3","B♭-4","B♭-4","C0","D♭-8"],["B7","C0","E♭-5"],["A♭-7","E6","C♯11","F♯9"],["A♭-7","C♭-11","A4"],["E6","B♭-4","E♭-5","F♯9"],["C♯11","A4","G1","F-2"],["E♭-5","E♭-5"],["C0","A4"],["G♭-10","C0","C0","E♭-5"],["E6","B7","C♯11","F♯9","F-2"],["D3","D3","G♭-10","C♭-11","F♯9"],["A♭-7","D3","D3","B♭-4","C0"],["C♯11","G1"],["D3","G♭-10"],["C♭-11","C0","C0"],["D3","D3","B7"],["E6","C♯11","F-2"],["D3","E♭-5","E♭-5","F-2"],["D3","C♭-11","C♯11","F-2"],["B7","B7","C0"]]},{"accuracy":0,"chordLabels":["B♭M","Do7","Ao7","A♭Mm7","B♭m","B♭M","Bm","GM","EM","FMm7","Cm","A♭m","AM","F♯Mm7","CM","D♭M","FM","Em","GMm7","AM","CM","AM","Do7","CMm7","G♭M","Fm","D♭M","D♭Mm7","F♯Mm7","Dm","B♭M","DM","Do7","AM","FM","D♭M","CM","CM","DM","F♯o7","D♭M","Fm","GM","DM","CMm7"],"likelihood":-14.910482228168174,"reruns":1,"runTime":4.0632e-5,"slices":[["D3","B♭-4"],["A♭-7","C♭-11","C♭-11","A4"],["G♭-10","B7","C0","A4","E♭-5"],["A♭-7","E6","G♭-10"],["D♭-8","G1","F-2"],["A♭-7","D3","G♭-10","B♭-4","A4"],["D3","B7","B♭-4","F♯9","F♯9"],["D3","E6","B7","E♭-5","F-2"],["E6","B7"],["E♭-5","F-2"],["D3","C0","E♭-5"],["A♭-7","C♭-11","E♭-5"],["C♯11","F-2"],["E6","C0","C♯11","F♯9"],["D3","E6","E6","E♭-5","F-2"],["A♭-7","D♭-8"],["A4","D♭-8"],["E6","E6","B7","C♯11","G1"],["D3","B7","D♭-8"],["C♯11","F-2"],["B7","C0","E♭-5"],["A♭-7","B7","C♯11","A4"],["A♭-7","C♭-11","A4"],["B♭-4","C0"],["G♭-10","G♭-10","G1"],["A♭-7","C♯11","F-2","F-2"],["A♭-7","A4","D♭-8"],["C♭-11","C0","D♭-8","A4"],["E6","B♭-4","C♯11","F♯9"],["D3","E6","F♯9","F-2","F-2"],["B♭-4","A4"],["D3","D3","A4","A4","G1"],["A♭-7","C♭-11","A4","F-2","F-2"],["C0","C♯11"],["C0","F-2"],["D♭-8","E♭-5","F-2"],["E6","C0"],["E6","E6","B7","C0"],["D3","E6","C0","B♭-4","F♯9"],["C♯11","C♯11","E♭-5","F♯9","F-2"],["A♭-7","A♭-7","A♭-7","D♭-8","F-2"],["A♭-7","F-2","F-2","F-2"],["D3","C♭-11","B7","E♭-5"],["G♭-10","F♯9"],["B♭-4","C0","F♯9"]]}]}