{"algorithm":"RandomSample","corpus":"chopin_mazurkas","groundTruth":["DMm7","Gm","D♯M","E♯Mm7","A♯M","DMm7","Gm","B♯m","Gm","B♯m","Gm","B♯m","DMm7","Gm","D♯M","E♯Mm7","A♯M","DMm7","Gm","Amm7","DMm7","DMm7","Gm","Gm","E♯Mm7","E♯Mm7","A♯M","E♯Mm7","E♯Mm7","A♯M","GMm7","B♯Mm7","E♯Mm7","A♯Mm7","D♯Mm7","G♯Mm7","C♯Mm7","F♯Mm7","B♯Mm7","E♯Mm7","A♯M","B♯Mm7","E♯Mm7","A♯M","GMm7","B♯Mm7","E♯Mm7","A♯Mm7","Eo7","E♯Mm7","E♯Mm7","E♯Mm7","A♯M","DM","DMm7","Gm","D♯M","E♯Mm7","A♯M","DMm7","Gm","B♯m","Gm","B♯m","Gm","B♯m","DMm7","Gm","D♯M","E♯Mm7","A♯M","DMm7","Gm","Amm7","DMm7","DMm7","Gm","Gm"],"id":"20230427123136_baselineExp","piece":"BI167op67-2","results":[{"accuracy":1.282051282051282e-2,"chordLabels":["Do7","B♭m","B♭m","C♭M","E♭Mm7","EMm7","Ao7","A♭M","CM","FM","AM","AM","FM","E♭M","D♭M","CMm7","BIt","D♭M","DMm7","Do7","B♭m","F♯o7","B♭M","BIt","CM","A♭M","AMm7","Do7","F♯Mm7","E♭Mm7","B♭M","C♯Mm7","B♭mm7","C♭M","DM","B♭M","FM","CMm7","EM","D♭M","CM","A♭m","C♯o","C♯Mm7","GM","D♭M","A♭M","GM","C♭M","A♭M","GM","C♯M","AM","Bm","DM","DM","A♭Mm7","C♯o7","GM","F♯Mm7","Bo7","E♭M","AM","DM","Ao7","B♭M","A♭Mm7","A♭M","FM","A♭Mm7","GM","A♭M","E♭M","B♭M","F♯M","DMm7","B♭M","DM"],"likelihood":-15.098855690251135,"reruns":1,"runTime":1.9032e-4,"slices":[["C♭-11","A4"],["B♭-4","D♭-8","D♭-8","F-2"],["B♭-4","C♯11","D♭-8"],["G♭-10","E♭-5"],["B7","D♭-8","E♭-5"],["D3","E6"],["G♭-10","A4","A4","G1","E♭-5"],["C0","E♭-5"],["A♭-7","E6","G1","G1","F-2"],["F-2","F-2"],["D3","E6","C♭-11","C♯11"],["A♭-7","C♯11"],["A♭-7","E6","D♭-8","F♯9"],["B♭-4","E♭-5"],["A♭-7","D♭-8"],["B♭-4","B♭-4","C0","C♯11","E♭-5"],["G♭-10","B7","D♭-8","D♭-8","F♯9"],["A♭-7","G♭-10","E6","C♯11","D♭-8"],["D3","C0"],["D3","C♭-11","F♯9"],["B♭-4","D♭-8","D♭-8","F♯9"],["C♭-11","E♭-5","F♯9"],["D3","B♭-4","A4","D♭-8"],["B7","D♭-8","D♭-8","A4","F♯9"],["E6","B7","C0","G1"],["C0","E♭-5"],["C♯11","G1","G1"],["C♭-11","F♯9"],["G♭-10","C♯11","D♭-8","F♯9"],["D3","D♭-8","D♭-8","E♭-5"],["D3","D3","E♭-5","F-2"],["B7","C♯11"],["A♭-7","B♭-4","B♭-4","C♯11","D♭-8"],["G♭-10","C♭-11","E♭-5","F-2"],["D♭-8","F♯9"],["D3","D3","G♭-10","B♭-4","C♯11"],["B♭-4","C0","A4","F-2"],["E6","B♭-4","C0","G1"],["E6","B7"],["D♭-8","D♭-8"],["B7","C0","D♭-8"],["C♭-11","E♭-5","F-2"],["E6","C♯11","G1","F♯9"],["B7","C♯11"],["D3","G♭-10","B7","B7","G1"],["A♭-7","E6","G♭-10","C♯11","D♭-8"],["A♭-7","E♭-5","F-2"],["B7","B7","D♭-8","G1"],["G♭-10","C♭-11","G1","E♭-5"],["C0","D♭-8","G1"],["D3","C♭-11","C♯11","G1"],["C♯11","C♯11","D♭-8"],["D3","E6","C0","C♯11"],["D3","B7","B7"],["B7","B♭-4","C♯11","A4","F-2"],["G♭-10","A4","D♭-8","F♯9"],["A♭-7","G♭-10","B♭-4","C0"],["E6","B7","C♭-11","B♭-4","C♯11"],["B7","C♭-11"],["E6","F♯9"],["A♭-7","B7"],["G♭-10","B7","C♭-11","B♭-4","G1"],["B♭-4","C♯11","A4"],["D3","A4"],["G♭-10","B♭-4","A4","A4","G1"],["D3","D3","B♭-4","F-2"],["G♭-10","G♭-10","C0"],["C♭-11","C0"],["B7","C0","F-2","F-2"],["G♭-10","C0"],["B7","G1","F♯9"],["A♭-7","A♭-7","B♭-4","C0","E♭-5"],["E♭-5","G1","F-2"],["B♭-4","A4"],["A♭-7","C♯11","F♯9"],["D3","C0","F♯9","F♯9"],["D3","B♭-4","D♭-8"],["D3","C♯11"]]},{"accuracy":1.282051282051282e-2,"chordLabels":["A♭Mm7","Cm","E♭Mm7","DM","F♯M","CMm7","GM","BM","Gm","DM","Eo7","AM","Gm","A♭Mm7","Ao7","AM","DMm7","D♭M","AMm7","A♭M","Fm","C♭M","AMm7","DMm7","G♭M","GM","E♭M","DM","E♭Mm7","F♯Mm7","E♭M","F♯o7","DM","A♭Mm7","Gm","G♭M","E♭M","DMm7","EM","FM","AM","Em","Ao7","FMm7","E♭+","Ao7","CM","D♭Mm7","EMm7","CM","E♭M","A♭M","BMm7","D♭Mm7","AM","E♭M","G♭M","A♭m","F♯o7","A♭Mm7","FM","GM","Ao7","E♭M","Ao7","EM","C♭M","C♭M","B♭M","CM","Ao7","GMm7","Cm","DM","GM","FM","GM","B♭M"],"likelihood":-14.73893109529264,"reruns":1,"runTime":7.8485e-5,"slices":[["A♭-7","A♭-7","G♭-10","B7","A4"],["C0","E♭-5","G1"],["D3","G♭-10","C0","D♭-8","G1"],["D3","D3","E6","F♯9"],["A♭-7","C♯11","F♯9"],["E6","G♭-10","C0","G1"],["D3","B7","D♭-8","G1","G1"],["B7","F♯9"],["D3","D♭-8","A4","G1"],["C♯11","G1","F♯9"],["E6","B7","B♭-4","C0","D♭-8"],["B♭-4","C♯11","A4"],["D3","D3","E6","D♭-8","G1"],["D3","A♭-7","G♭-10"],["G♭-10","A4"],["E6","B7","C♯11","F-2"],["D3","E6","C0","F♯9"],["A♭-7","A♭-7","G♭-10","D♭-8"],["E6","C♯11","G1"],["A♭-7","A♭-7","C♯11","E♭-5"],["A♭-7","F-2","F-2"],["G♭-10","G♭-10","C♭-11","C♭-11"],["A4","G1"],["D3","C0","F♯9"],["G♭-10","G♭-10","G1"],["G1","F♯9"],["C♭-11","C♭-11","B♭-4","G1","F-2"],["D3","A4","A4","E♭-5"],["B♭-4","D♭-8","A4","E♭-5"],["E6","F♯9"],["B♭-4","G1"],["C0","G1","E♭-5","F♯9","F♯9"],["D3","D3","C♯11","A4"],["A♭-7","A♭-7","G♭-10","F♯9"],["D3","D3","B♭-4","A4","G1"],["G♭-10","D♭-8"],["D3","E6","E♭-5","E♭-5"],["D3","C0"],["E6","B7"],["B♭-4","C0","A4"],["C♯11","F-2"],["B7","B7","C0","B♭-4","C♯11"],["E6","G♭-10","C0","E♭-5"],["A4","E♭-5","G1","F♯9","F-2"],["C♭-11","B7","E♭-5","F♯9"],["G♭-10","E6","C0","A4","E♭-5"],["C♭-11","B7","C0","B♭-4","A4"],["C♭-11","D♭-8","F-2","F-2"],["D3","E6","B7"],["B7","C0","C0","G1","F♯9"],["B♭-4","E♭-5"],["C0","E♭-5"],["B7","A4","A4"],["C♭-11","C♯11","D♭-8","A4"],["D3","E6","B7","C♯11","D♭-8"],["C♭-11","B♭-4","D♭-8","G1","F♯9"],["G♭-10","G♭-10"],["C♭-11","E♭-5","F-2"],["C0","C♯11","E♭-5"],["A♭-7","G♭-10"],["D♭-8","A4","G1"],["B7","E♭-5"],["G♭-10","C♭-11","A4","E♭-5","G1"],["B♭-4","G1"],["G♭-10","G♭-10","A4"],["E6","B7"],["G♭-10","C♭-11"],["A♭-7","G♭-10","C♭-11","C♭-11"],["D3","C0","D♭-8"],["C♭-11","B7","C0"],["E6","G♭-10"],["B7","C♯11","G1","F-2"],["D3","G♭-10","C♯11","E♭-5","G1"],["D3","E♭-5","F♯9"],["D3","B7"],["C0","F-2"],["D3","C♭-11","G1","G1","F♯9"],["B♭-4","A4"]]},{"accuracy":1.282051282051282e-2,"chordLabels":["Do","E♭M","Fm","D♭M","CMm7","D♭Mm7","G♭M","E♭Mm7","A♭M","FMm7","FM","F♯%7","FM","DM","C♭M","GMm7","C♯Ger","CM","Gm","C♯o7","CM","CM","Do7","Bo7","FMm7","GM","B♭Mm7","FM","AMm7","B♭M","B♭Mm7","G♭M","EMm7","F♯o7","A♭M","FM","Ao","C♭M","FM","Do7","DM","FMm7","E♭Mm7","E♭M","A♭Mm7","FM","C♭M","Gm","GMm7","Do7","E♭M","CM","A♭M","B♭m","Ao7","G♭M","EMm7","A♭mm7","A♭M","DM","CM","F♯Mm7","DM","Do7","G♭M","GM","B♭M","CM","C♭M","Co","A♭M","AM","EM","AMm7","DM","E♭M","AM","DM"],"likelihood":-15.611599908569392,"reruns":1,"runTime":4.3235e-5,"slices":[["A♭-7","D3","E6","E♭-5","F-2"],["E6","B♭-4","G1","E♭-5"],["A♭-7","C♭-11","A4","G1","F-2"],["A♭-7","D♭-8","A4"],["G♭-10","B♭-4","C0","G1","F♯9"],["A♭-7","C♭-11","C♯11","D♭-8","F♯9"],["G♭-10","C♭-11","B7","D♭-8"],["B♭-4","D♭-8","G1"],["A♭-7","B♭-4","E♭-5"],["A♭-7","B7","A4","E♭-5"],["A♭-7","E6","F♯9","F-2"],["E6","C0","D♭-8","A4","F♯9"],["A♭-7","E6","F♯9","F-2"],["D3","C♯11","F♯9","F♯9"],["G♭-10","C♭-11"],["D3","D3","B7","D♭-8","F-2"],["A♭-7","C♯11","C♯11","C♯11","E♭-5"],["D3","E6","E6","C0","D♭-8"],["D3","E6","C♭-11","B♭-4","A4"],["D3","E6","C♭-11","B♭-4","C♯11"],["E6","C0","C0"],["B7","C0","C♯11","D♭-8","G1"],["A♭-7","D3","D3","C♭-11","F♯9"],["A♭-7","B7","E♭-5","F♯9"],["C♭-11","A4","E♭-5"],["D3","B7","B♭-4","G1","F♯9"],["A♭-7","D3"],["D♭-8","A4"],["A4","G1","G1"],["A♭-7","B7","B♭-4","A4","E♭-5"],["A♭-7","B♭-4"],["G♭-10","G♭-10"],["A♭-7","D3","E6","B7"],["C0","E♭-5","F♯9"],["A♭-7","A♭-7","C0","C♯11"],["E6","F-2"],["B7","A4","E♭-5","E♭-5"],["G♭-10","B7","C♭-11","E♭-5","F-2"],["E6","A4","F-2"],["A♭-7","C♭-11","A4"],["G♭-10","F♯9"],["E♭-5","F-2"],["C♯11","D♭-8","G1","E♭-5","F-2"],["B♭-4","B♭-4","E♭-5","F♯9"],["A♭-7","G♭-10","C♭-11","G1"],["C0","C♯11","D♭-8"],["A♭-7","G♭-10","C♭-11"],["D3","D♭-8","G1"],["B7","F-2"],["D3","C♭-11"],["D3","E♭-5"],["E6","C0","G1"],["C0","E♭-5"],["A♭-7","B♭-4","D♭-8","E♭-5","F♯9"],["G♭-10","C♭-11","C♯11","D♭-8","A4"],["G♭-10","C♭-11","B♭-4","C0","D♭-8"],["D3","E6"],["A♭-7","G♭-10","C♭-11","C♭-11","C♯11"],["A♭-7","C0","E♭-5"],["E6","B♭-4","F♯9"],["D3","E6","C♭-11","C0","A4"],["A♭-7","E6","F♯9"],["D3","C♯11","F♯9"],["D3","C♭-11"],["G♭-10","G♭-10"],["E♭-5","G1","F♯9"],["D3","B♭-4","C0"],["E6","E6","C♭-11","G1","E♭-5"],["G♭-10","C♭-11","C♭-11","C0"],["E6","G♭-10","C0","D♭-8"],["C♭-11","C0","D♭-8","G1","F♯9"],["C♯11","C♯11","A4","D♭-8"],["E6","B7"],["E6","C♯11","G1"],["D3","D3","F♯9"],["D3","E♭-5"],["C♯11","D♭-8","A4"],["G♭-10","G1","F♯9","F♯9"]]},{"accuracy":3.8461538461538464e-2,"chordLabels":["BM","D♭M","GM","Ao7","B%7","B♭M","CM","E♭m","D♭M","AM","DMm7","F♯o7","GMm7","F♭M","FMm7","A♭m","Eo7","E♭M","FM","G♭M","DMm7","E♭M","DM","F♯M","B♭M","EM","DMm7","Do7","Fm","B♭m","DM","DM","Ao7","GMm7","F♯%7","C♯Mm7","GM","A♭Mm7","Do7","E♭M","CMm7","AM","AMm7","CMm7","C♭M","F♯M","C♯%7","Gm","F♭M","AM","Eo7","A♭m","AM","DM","CM","DM","C♭M","A♭Mm7","Em","DM","DM","F♯o7","Eo","CM","DM","GMm7","B♭m","DM","Do","A♭♭M","G♭M","CM","G♭M","C♭M","Do","Em","A♭M","Gm"],"likelihood":-16.435568829477248,"reruns":1,"runTime":3.6008e-5,"slices":[["B7","C♯11","F♯9"],["D3","C♯11","D♭-8","D♭-8"],["D3","B7","B7","E♭-5","F♯9"],["G♭-10","B7","C♯11","E♭-5"],["D3","B7","A4","A4","D♭-8"],["B♭-4","B♭-4","A4","E♭-5","F-2"],["A♭-7","E6"],["G♭-10","B7","E♭-5"],["C0","C0","D♭-8","D♭-8"],["D3","B7","C0","C♯11"],["D3","C♭-11","C0","C♯11"],["C0","E♭-5","F♯9"],["G♭-10","G1","F♯9","F-2"],["A♭-7","C♭-11"],["A4","E♭-5"],["A♭-7","C♭-11","C♭-11","B♭-4"],["B7","D♭-8","D♭-8"],["G♭-10","B7","G1","E♭-5"],["E6","F-2"],["G♭-10","G♭-10","D♭-8","G1"],["D3","G♭-10","C0","F♯9","F♯9"],["C0","B♭-4","E♭-5","G1"],["D3","C♯11","G1","F♯9","F♯9"],["F♯9","F♯9"],["D3","D♭-8","F-2"],["A♭-7","E6","B7","F♯9"],["C0","F♯9"],["C♭-11","F♯9"],["A♭-7","F-2","F-2"],["C0","B♭-4","C♯11","D♭-8"],["B♭-4","F♯9"],["D3","B♭-4","C♯11"],["D3","G♭-10","C♯11","E♭-5"],["G1","F-2"],["G♭-10","E6","C0","F♯9"],["G♭-10","B7","C♯11"],["D3","D3","E6","B7","C0"],["G♭-10","B7","C♭-11","C0"],["D3","C♭-11","C♭-11","B♭-4"],["G1","G1","E♭-5"],["E6","B♭-4"],["C♯11","A4"],["E6","E6","A4","G1"],["E6","B♭-4"],["G♭-10","C♭-11","B♭-4"],["G♭-10","F♯9","F♯9"],["B7","C♭-11","C♯11","C♯11"],["B♭-4","A4","G1"],["A♭-7","C♭-11","C♭-11"],["E6","C♯11","A4"],["G♭-10","E6","B7","D♭-8"],["A♭-7","A♭-7","C♭-11"],["C♯11","A4","A4","G1","F♯9"],["D3","D3","B♭-4","C♯11"],["D3","C0","G1"],["D3","C♯11","D♭-8"],["G♭-10","G♭-10","C♭-11","B7","E♭-5"],["A♭-7","G♭-10","E♭-5","F♯9"],["E6","B7","G1"],["A♭-7","B♭-4","C♯11","A4","F♯9"],["D3","D3","C♯11","D♭-8"],["A4","E♭-5","F♯9","F♯9"],["E6","E6","B♭-4","B♭-4","A4"],["E6","E6","C0"],["A4","F♯9"],["D3","D♭-8","G1","F♯9"],["A♭-7","B♭-4","B♭-4","D♭-8","F-2"],["E6","F♯9","F-2"],["A♭-7","B7","E♭-5","F-2","F-2"],["G♭-10","C♭-11","C♯11"],["G♭-10","G♭-10","F♯9"],["E6","E♭-5"],["D3","G♭-10","G♭-10"],["C♭-11","C♭-11"],["A♭-7","A♭-7","D3","E6","F-2"],["B7","C0","C♯11","G1","F♯9"],["C♭-11","C♯11","D♭-8","E♭-5","E♭-5"],["D3","B♭-4","G1"]]}]}