{"algorithm":"RandomSample","corpus":"ABC","groundTruth":["CM","GMm7","GMm7","G♯o7","Am","Dmm7","DMm7","GM","GM","DMm7","GMm7","CM","GMm7","GMm7","G♯o7","Am","Dmm7","DMm7","GMm7","CM","GMm7","GMm7","CM","CM","GMm7","GMm7","G♯o7","Am","Dmm7","DMm7","GM","GM","DMm7","GMm7","CM","GMm7","GMm7","G♯o7","Am","Dmm7","DMm7","GMm7","CM","GMm7","GMm7","CM","GM","DMm7","GM","G♯o","CM","GM","CM","GMm7","CM","GMm7","GM","DMm7","DMm7","GM","GMm7","GMm7","CM","GMm7","GMm7","G♯o7","Am","Dmm7","DMm7","GMm7","EMm7","Am","E♯M","GMm7","CM","E♯M","E♯M","GM","GMm7","GMm7","CM","GMm7","GMm7","CM","GMm7","GMm7","CM","E♯M","E♯M","CM","CMm7","E♯M","E♯M","CM","CMm7","E♯M","CM","GMm7","CM","CM","CM","GMm7","CM","CM","CM","GMm7","CM","GMm7","CM","GMm7","AM","AM","Dm","AM","AMm7","Dm","GM","Eo","GM","GMm7","Eo","Eo","CM","CM","E♯M","CM","CMm7","E♯M","CM","CMm7","E♯M","CM","CMm7","E♯M","CM","CMm7","E♯M","CM","CMm7","CM","CMm7","CM","CMm7","GMm7","GMm7","Cm","E♯m","GMm7","GMm7","GMm7","D♯M","G♯M","G♯M","E♯m","Do","G♯o7","G♯o7","GM","Cm","GM","Cm","Cm","GM","GM","F♯It","F♯o7","E♯m","GMm7","GMm7","GM"],"id":"20230427123345_baselineExp","piece":"n09op59-3_03","results":[{"accuracy":1.764705882352941e-2,"chordLabels":["F♯o7","AMm7","AM","C♯o7","FMm7","DMm7","C♯o7","Do7","E♭M","Eo7","Eo7","Ao7","DM","D♭Mm7","F♯Mm7","BMm7","B♭M","C♭M","Eo7","GM","F♯o7","FMm7","GM","B♭M","C♭M","A♭m","A♭Mm7","EIt","B♭m","E♭M","E♭M","Fm","CMm7","FM","C♯o7","C♭M","F♯M","D♭M","CMm7","B♭Mm7","AM","F♯o7","Bm","FM","Ao7","G♭M","Eo7","GM","F♯Mm7","E♭M","AM","FM","F♯o7","A♭M","Do7","FMm7","D♭M","A♭M","Am","CM","GM","EMm7","Bo7","EMm7","F♯o7","GM","Bo7","DM","E♭Mm7","Ao7","Ao7","A♭M","G♭M","EMm7","Bo7","Bo7","AMm7","A♭Mm7","AM","F♯o7","FM","Cm","GMm7","GM","B♭m","DM","CMm7","AMm7","D♭Mm7","AM","AM","E♭M","Go","GM","E♭M","GM","FMm7","B♭M","G♭M","GM","C♯o7","GM","A♭M","DM","E♭M","E♭M","A♭Mm7","DM","AM","GM","D♭Mm7","Do7","Dm","A♭Mm7","F♯o7","A♭M","D♭Mm7","B♭Mm7","EMm7","DM","AM","Do7","D♭Mm7","C%7","E♭M","B♭M","GM","Ao7","CMm7","CMm7","FM","A♭M","CM","AMm7","G♭M","CM","Ao7","FMm7","CM","DM","AM","CMm7","C♭M","D♭M","A♭m","CM","D♭M","F♯M","GM","Eo7","B♭M","E♭Mm7","CM","DM","DM","FMm7","C♯%7","DM","D♭M","DM","AM","A♭M","FM","A♭Mm7","Bm","E♭Mm7","Bo7","A♭Mm7","B♭M","FM"],"likelihood":-15.060275972943847,"reruns":1,"runTime":1.5609e-4,"slices":[["D3","C♭-11","C0","E♭-5","F♯9"],["C♯11","A4","D♭-8","G1"],["E6","C0","C♯11"],["B♭-4","B♭-4","C♯11","A4"],["C♭-11","A4","A4"],["C0","F♯9"],["E6","E6","B♭-4","C♯11"],["D3","C♭-11","D♭-8","F♯9","F-2"],["G♭-10","G1","G1"],["E6","D♭-8","D♭-8","G1","F♯9"],["E6","E6","D♭-8"],["G♭-10","A4"],["D3","E♭-5","F♯9"],["A♭-7","C♭-11","C♯11"],["G♭-10","C♯11","D♭-8","F♯9"],["B7","A4","A4"],["D3","D3","D3","G♭-10"],["G♭-10","C♭-11","C♭-11","E♭-5","G1"],["E6","B7","B♭-4","D♭-8"],["B7","E♭-5"],["C♯11","E♭-5","G1","F♯9"],["B7","E♭-5","F-2"],["G♭-10","B7"],["D3","G♭-10","C0"],["G♭-10","E♭-5"],["C♭-11","C♭-11","C♯11","E♭-5"],["G♭-10","C0"],["G♭-10","E6","C♭-11","B7","F-2"],["C0","B♭-4","D♭-8","F♯9"],["D3","G♭-10","C0","B♭-4","G1"],["D3","B♭-4","E♭-5"],["A♭-7","A♭-7","C0","C♯11","A4"],["E6","G♭-10","G1"],["C♭-11","B♭-4","C0","F♯9","F-2"],["E6","E6","B♭-4","C♯11"],["C♭-11","C♭-11","C♭-11","B♭-4"],["G♭-10","C♯11","C♯11","C♯11"],["D♭-8","E♭-5","F-2"],["E6","B♭-4","G1"],["A♭-7","D3","D3"],["B7","C0","C♯11","F-2"],["A♭-7","E♭-5","F♯9"],["D3","D3","G♭-10","B7","C♯11"],["D♭-8","A4","F-2"],["G♭-10","C♭-11","A4"],["G♭-10","G♭-10","B♭-4"],["E6","D♭-8"],["G♭-10","B7"],["E6","E6","F♯9"],["G♭-10","B7","B♭-4","G1"],["A♭-7","E6","C0","C♯11","A4"],["G♭-10","C♯11","A4","F-2"],["C♯11","E♭-5"],["A♭-7","E♭-5"],["D3","C♭-11"],["E♭-5","F-2"],["A♭-7","A♭-7","G♭-10","A4","D♭-8"],["C♭-11","C0","G1","E♭-5","E♭-5"],["E6","A4","A4","E♭-5"],["E6","C0"],["B7","C♭-11","B♭-4","F♯9"],["D3","E6"],["A♭-7","A♭-7","E6","B7","F♯9"],["D3","E6","C♭-11"],["C♭-11","C0","F♯9"],["B7","E♭-5"],["A♭-7","E6","B7","B7","F-2"],["D3","A4","A4","A4"],["D3","G♭-10","D♭-8","E♭-5","F♯9"],["D3","E6","G♭-10","C♭-11","A4"],["G♭-10","G♭-10","C♯11","G1","E♭-5"],["C♭-11","C0","C0","D♭-8","F♯9"],["G♭-10","C♭-11","D♭-8","G1"],["D3","E6","E6"],["A♭-7","D3","B7","B7"],["A♭-7","B7","C0","C♯11","D♭-8"],["B7","A4","A4","G1"],["A♭-7","G♭-10","C0","C♯11"],["A♭-7","E6","C♯11"],["C0","E♭-5","F♯9"],["E6","F-2"],["G♭-10","C0","G1"],["B7","F-2"],["D3","B7"],["B♭-4","C0","D♭-8","F♯9"],["G1","F♯9","F♯9"],["B♭-4","C0"],["E6","C♯11","G1"],["A♭-7","C♭-11","D♭-8","G1"],["C♯11","D♭-8"],["A♭-7","E6","B7","C♯11","F♯9"],["A♭-7","B♭-4","E♭-5","E♭-5"],["A♭-7","B7","D♭-8","G1"],["E6","G♭-10","G1","F♯9","F-2"],["D3","C♭-11","B♭-4","G1","E♭-5"],["D3","G1"],["C♯11","G1","E♭-5","F-2"],["B7","B♭-4","F-2"],["G♭-10","B♭-4","F-2"],["B7","B♭-4","G1"],["B♭-4","C♯11"],["D3","G1"],["A♭-7","E♭-5"],["D3","F♯9","F♯9"],["E6","C♭-11","C♭-11","B♭-4","G1"],["B7","C♭-11","D♭-8","G1"],["A♭-7","G♭-10"],["D3","D3","C♭-11","C♯11"],["A♭-7","B7","C♯11","A4"],["C♭-11","B7"],["C♭-11","D♭-8"],["A♭-7","C♭-11","F♯9","F-2"],["D3","A4","F-2"],["G♭-10","C0"],["D3","C♯11","A4","E♭-5","E♭-5"],["C0","E♭-5","E♭-5"],["C♭-11","D♭-8","G1"],["A♭-7","D3","C0","B♭-4","C♯11"],["D3","A♭-7","E6","B7"],["C♯11","G1","F♯9"],["C♯11","D♭-8"],["D3","C♭-11","C♭-11","C♯11","A4"],["C♭-11","D♭-8","G1"],["G♭-10","B♭-4","C0","E♭-5","F♯9"],["E6","C♭-11","D♭-8","G1","E♭-5"],["D3","B7","C0","D♭-8","E♭-5"],["G♭-10","B7","B7","G1","F♯9"],["G♭-10","E6"],["D3","E6","B♭-4","C0","C♯11"],["E6","B♭-4"],["D3","E6","A4","D♭-8","E♭-5"],["A♭-7","G1"],["E6","C0","D♭-8"],["E6","C♯11","C♯11","G1","E♭-5"],["G♭-10","F-2"],["D3","E6","C0","C0"],["E6","C♭-11","B♭-4","A4"],["E♭-5","F-2","F-2"],["E6","C♭-11"],["D♭-8","F♯9"],["A♭-7","E6","C♯11","A4","E♭-5"],["C0","B♭-4"],["G♭-10","E♭-5"],["C0","D♭-8","D♭-8"],["A♭-7","G♭-10","C♭-11","C♭-11","A4"],["E6","B7","G1","E♭-5"],["A♭-7","F-2"],["C♯11","F♯9","F-2"],["A♭-7","B7","B♭-4","A4","G1"],["E6","B♭-4","A4","D♭-8"],["C0","B♭-4","F-2"],["D♭-8","A4","G1","G1","E♭-5"],["C♭-11","C♯11","G1","F-2"],["D3","C♯11","G1"],["D3","G♭-10","C♯11","A4"],["A♭-7","C0","C♯11","A4","E♭-5"],["C♭-11","B7","C♯11"],["D♭-8","F♯9"],["A♭-7","C♯11","D♭-8","E♭-5","F-2"],["G1","F♯9","F♯9","F-2"],["E6","E6","C♯11","C♯11","D♭-8"],["A♭-7","A♭-7"],["A4","D♭-8","G1","F-2"],["A♭-7","G♭-10","C♭-11","A4","G1"],["B7","F♯9","F-2"],["D♭-8","G1"],["A♭-7","B7"],["A♭-7","G♭-10","B7","C0"],["B♭-4","B♭-4","F♯9"],["A4","A4","A4","D♭-8"]]},{"accuracy":5.8823529411764705e-3,"chordLabels":["FM","AMm7","Fm","A♭m","Ao7","B♭M","E♭Mm7","B♭M","Cm","C♯Ger","D♭M","D♭+7","DM","A♭M","DM","Do7","GMm7","CM","Eo7","A♭M","B♭M","F♯o7","C♭M","BMm7","E♭M","C♭M","Bo7","D♭Mm7","Fm","Bo","D♭M","E♭+","Eo7","CM","Ao7","D♭M","CM","FM","E♭Mm7","FMm7","B♭M","CM","Eo7","AMm7","DM","Cm","AM","A♭Mm7","D♭Mm7","Ao7","DMm7","Do7","A♭M","Gm","DM","A♭mm7","Eo","CM","D♭M","FM","D♭M","D♭Mm7","DM","D♭M","E♭M","C♭M","CMm7","Cm","F♯Mm7","GM","E♭m","CMm7","FM","Gm","Cm","A♭Mm7","FM","A♭Mm7","FMm7","B♭M","B♭M","CMm7","DMm7","GM","B♭M","D♭Mm7","A♭Mm7","AM","Ao","C♭M","AM","Em","E♭Mm7","Dm","C♭M","AM","FM","Bo7","GMm7","AMm7","Bo7","CM","Bo7","Do7","FMm7","C♯%7","E♭M","C♭M","B♭M","Eo7","Ao7","AMm7","GM","BM","E♭Mm7","DMm7","F♭M","DM","Eo7","E%7","Fm","AM","B♭M","A♭mm7","B♭Mm7","D♭M","Do7","A♭Mm7","E♭M","FM","A♭M","FM","A♭♭M","F♯o7","FM","B♭M","CM","CM","A♭Mm7","Bm","E♭M","EM","F♯Mm7","DM","Ao7","Bo7","AM","DMm7","FM","B♭+","AM","EM","C♭M","CM","Co","A♭Mm7","AM","A♭M","FM","A♭M","DM","B♭m","D♭Mm7","Do7","E♭M","FM","E♭M","AMm7","AM","Dm"],"likelihood":-15.905301405777742,"reruns":1,"runTime":1.05335e-4,"slices":[["A♭-7","A4"],["E6","C0","C♯11","C♯11","E♭-5"],["A♭-7","C0","F-2"],["A♭-7","G♭-10","C♭-11","C♭-11","C0"],["G♭-10","E6","E6","C♭-11"],["D3","D3","G♭-10","G1","F-2"],["D♭-8","E♭-5","G1","F-2"],["D3","B♭-4","A4"],["D3","G♭-10","C0","G1"],["C♯11","C♯11","D♭-8","E♭-5"],["D♭-8","F-2"],["C♭-11","D♭-8","A4","F♯9"],["D3","G♭-10","F♯9"],["A♭-7","C♯11","D♭-8","E♭-5"],["D3","G♭-10","B♭-4","C♯11","A4"],["D3","D3","C♭-11","C0"],["G1","F-2"],["B7","C0","C0","C♯11"],["E6","D♭-8"],["A♭-7","E6","D♭-8","E♭-5"],["D3","G♭-10","E6","D♭-8","F-2"],["A♭-7","E♭-5","G1","F♯9"],["C♭-11","D♭-8","E♭-5"],["B7","A4"],["E6","B♭-4","E♭-5","F-2"],["G♭-10","C♭-11","B7","C0","D♭-8"],["D3","A♭-7","F♯9","F-2"],["C♭-11","F-2"],["C♭-11","C0","F-2"],["B7","B7","C0","B♭-4","F-2"],["D♭-8","D♭-8","F♯9"],["G♭-10","B7","B♭-4","E♭-5","F♯9"],["E6","B♭-4","A4","D♭-8"],["A♭-7","E6","C♯11","E♭-5"],["G♭-10","E6"],["C0","D♭-8","F-2"],["E6","B7","G1","E♭-5","F-2"],["E6","C0","D♭-8","F-2"],["E6","D♭-8","G1","E♭-5"],["C♭-11","C0","E♭-5","E♭-5","F-2"],["D3","C0","D♭-8"],["D3","G♭-10","E6","C0"],["E6","D♭-8","G1","F♯9"],["C♯11","G1"],["D3","A♭-7","C♯11","A4","G1"],["C0","C0","E♭-5"],["C♭-11","C0","C♯11","C♯11","C♯11"],["A♭-7","G♭-10","E♭-5"],["A♭-7","C♭-11","C♭-11","C♯11"],["G♭-10","G♭-10","A4"],["C0","C♯11","A4","F♯9","F-2"],["A♭-7","C♭-11","F♯9"],["A♭-7","E♭-5"],["G♭-10","B♭-4","A4","G1","G1"],["G♭-10","F♯9"],["A♭-7","G♭-10","C♭-11","C♯11","E♭-5"],["B7","B♭-4","C♯11","D♭-8","G1"],["E6","E6","C0","C0","E♭-5"],["A♭-7","B♭-4","C0","D♭-8"],["A♭-7","A4"],["D♭-8","F-2"],["C♭-11","D♭-8","D♭-8","A4"],["G♭-10","F♯9"],["A♭-7","A♭-7","G♭-10","D♭-8"],["B♭-4","G1"],["G♭-10","G♭-10","G♭-10","C♭-11","C0"],["E6","E6","G♭-10"],["C0","C0","G1","E♭-5","F♯9"],["E6","F♯9"],["D3","B7","B7","E♭-5","F-2"],["E6","G♭-10","E♭-5","F-2"],["E6","B♭-4"],["A♭-7","A4","F-2"],["B♭-4","D♭-8","A4","G1","G1"],["G♭-10","C0","E♭-5","G1","F♯9"],["A♭-7","G♭-10","B7"],["C0","D♭-8","F♯9"],["G♭-10","C♭-11","C0","G1","F-2"],["A♭-7","D3","E6","A4","E♭-5"],["D3","G♭-10","B♭-4","A4"],["B♭-4","F♯9","F-2"],["E6","E6","C♭-11","B♭-4"],["D3","D3","C0","F♯9","F♯9"],["D3","D3","B7","B♭-4","C0"],["D3","D3","B♭-4","F-2"],["C♭-11","C0","D♭-8","E♭-5","F-2"],["A♭-7","G♭-10","E6","G1"],["C♯11","C♯11","A4"],["B7","C0","C0","A4","E♭-5"],["C♭-11","E♭-5"],["D3","C♯11","A4","A4"],["E6","B7","B♭-4"],["B♭-4","D♭-8","G1"],["A♭-7","D3","C♯11","G1","F-2"],["C♭-11","E♭-5"],["D3","C♯11","C♯11","F-2"],["A♭-7","G♭-10","E6","C♯11","F-2"],["A♭-7","A♭-7","D3","B7","G1"],["B7","F-2"],["E6","A4","G1","F♯9"],["A♭-7","B7","C0","D♭-8","F♯9"],["C♭-11","C♯11","G1","F-2"],["A♭-7","A♭-7","D3","B7","A4"],["D3","C♭-11"],["A4","A4","E♭-5","E♭-5"],["B7","C♯11","D♭-8","G1"],["A♭-7","D3","E♭-5"],["G♭-10","E6","C♭-11"],["B♭-4","F-2"],["D3","E6","B7","D♭-8","E♭-5"],["G♭-10","C0","B♭-4","A4","G1"],["C♯11","G1"],["G1","F♯9"],["E6","B7","C♯11","F♯9"],["D3","D♭-8","E♭-5","E♭-5","F-2"],["D3","C0"],["A♭-7","C♭-11"],["B♭-4","F♯9"],["E6","G♭-10","D♭-8"],["D3","E6","E6","G♭-10","F-2"],["A♭-7","D3","C♭-11","C♯11","G1"],["C♯11","F-2"],["D3","B♭-4","D♭-8","D♭-8","A4"],["A♭-7","G♭-10","C♭-11","B♭-4","C♯11"],["A♭-7","B♭-4"],["C0","D♭-8"],["D3","C♭-11","A4"],["A♭-7","G♭-10","F♯9"],["B♭-4","B♭-4","E♭-5","F♯9"],["A♭-7","C♯11","F♯9","F-2"],["A♭-7","C0","E♭-5","E♭-5","F-2"],["B♭-4","C♯11","A4","D♭-8","F-2"],["C♭-11","C♯11"],["A♭-7","C♭-11","C♯11","F♯9"],["C0","C0","B♭-4","A4","A4"],["D3","B7","C0","D♭-8","E♭-5"],["D3","A♭-7","C0","C♯11","G1"],["E6","E6","C♭-11"],["A♭-7","G♭-10"],["D3","E6","B7","F♯9"],["G♭-10","G1","G1","E♭-5","F♯9"],["E6","B7"],["E6","C♯11","F♯9","F♯9"],["D3","A4"],["G♭-10","C0","D♭-8","A4"],["A♭-7","B7","B7","C0","A4"],["A♭-7","E6","C♯11"],["C0","F♯9"],["G♭-10","E6","F♯9","F-2","F-2"],["G♭-10","G♭-10","B♭-4","F♯9","F♯9"],["C♯11","C♯11","A4","D♭-8","E♭-5"],["E6","B7"],["G♭-10","C♭-11","B7"],["C0","C0"],["G♭-10","C0","D♭-8","G1"],["D3","A♭-7","E6","G♭-10","C♭-11"],["E6","E6","C♯11","D♭-8"],["A♭-7","A♭-7","G♭-10","C0","F-2"],["F-2","F-2"],["C0","E♭-5"],["B♭-4","F♯9","F♯9"],["D♭-8","D♭-8","G1","F-2","F-2"],["A♭-7","C♭-11","F-2"],["A♭-7","C♭-11","B♭-4","F♯9"],["D3","E♭-5"],["C0","C♯11","F-2"],["C♭-11","B♭-4","G1","F♯9"],["C♯11","G1","G1"],["A♭-7","B7","C♯11","A4"],["B7","A4","A4","G1","F-2"]]},{"accuracy":2.3529411764705882e-2,"chordLabels":["B♭M","AM","DMm7","BM","E♭M","Bm","B♭M","B♭M","F♯M","GM","EM","Go","BM","E♭m","A♭M","GM","CM","CM","FM","GM","D♭Mm7","BMm7","Ao7","Ao7","CM","E♭M","A♭M","FM","A♭M","C♭M","GMm7","B♭+","C♯o7","B♭M","D♭Mm7","C♭M","GM","C♯m","E♭M","Bo7","F♯M","C♭M","GM","E♭M","EMm7","D♭M","AMm7","FM","FMm7","FM","DM","AM","F♯o7","Ao7","G♭M","GMm7","Bo","C♭M","GM","B♭M","AM","D♭M","D♭M","DM","E♭Mm7","AM","B♭M","G♭M","C♭M","Bo7","FM","A♭Mm7","Do","E♭Mm7","CM","DM","FM","A♭M","A♭M","D♭Mm7","AMm7","Co","Co","GM","B♭M","AGer","GM","Go","FM","AMm7","A♭M","G♭M","A♭Mm7","B♭+","Eo7","F♯m","FMm7","Bo7","DM","AIt","CM","DM","CM","Em","DM","F♯Mm7","C♭M","A♭Mm7","E♭mm7","Bm","Do","DM","CM","B♭Mm7","BM","F♯M","B♭M","GM","C♭M","B♭M","G♭M","E♭+","Fm","Eo7","D♭M","FM","D♭Mm7","G♭M","GM","AM","B♭Mm7","FM","F♯o7","GM","DM","EM","D♭Mm7","Fm","Ao7","Cm","Eo7","Do7","E♭m","CMm7","CMm7","EMm7","FM","G♭M","E♭M","DM","Do7","A♭M","EM","C♯o7","F♯o7","Cm","D♭Mm7","F♯o7","D♭Mm7","E♭Mm7","F♯o7","Ao7","Eo7","D♭M","FM","GM","Do7","CMm7","D♭Mm7","G♭M"],"likelihood":-15.455651780622423,"reruns":1,"runTime":9.2601e-5,"slices":[["D3","B♭-4","B♭-4","D♭-8"],["C0","C♯11"],["D3","C0","C♯11","A4"],["E6","G♭-10","B7","F♯9"],["C♭-11","D♭-8","G1","G1"],["G♭-10","E6","B7","F♯9","F-2"],["D3","B♭-4"],["B♭-4","F-2"],["C♯11","F♯9","F-2"],["B7","B♭-4","G1"],["A♭-7","E6","B7"],["D3","D♭-8","D♭-8","G1"],["B7","B♭-4","F♯9"],["G♭-10","B♭-4","C0"],["A♭-7","E6","C♭-11","E♭-5","G1"],["B7","B♭-4","G1","E♭-5","F♯9"],["B7","C0"],["E6","C0","A4","E♭-5","G1"],["B♭-4","A4","F-2","F-2"],["B♭-4","G1","G1","F♯9"],["A♭-7","C♭-11","D♭-8","D♭-8"],["G♭-10","B7","A4"],["G♭-10","G♭-10","C♯11","F♯9"],["G♭-10","C♭-11","C♯11","E♭-5"],["E6","G1"],["D3","A♭-7","B♭-4","G1"],["A♭-7","C♭-11","C0","C♯11","E♭-5"],["A♭-7","A4","F-2"],["C♭-11","C0","D♭-8","E♭-5","F♯9"],["G♭-10","C♭-11","E♭-5"],["D3","D♭-8","G1","F-2"],["G♭-10","B♭-4","C♯11","F♯9","F-2"],["D3","E6","B♭-4","C♯11","E♭-5"],["D3","F-2"],["C♭-11","C♭-11","D♭-8","A4","F-2"],["C♭-11","B♭-4"],["D3","B7","C0","E♭-5"],["E6","C♯11","C♯11"],["B♭-4","E♭-5","G1","F♯9"],["A♭-7","B7","B7","C0","F-2"],["F♯9","F♯9"],["G♭-10","C♭-11"],["B7","G1","G1","E♭-5"],["B♭-4","E♭-5"],["D3","E6","B7"],["A♭-7","F-2"],["C♭-11","A4","G1"],["A4","D♭-8"],["A4","E♭-5"],["E6","F-2"],["D3","F♯9"],["E6","E6","C♯11","F-2"],["C0","C0","C♯11","C♯11","E♭-5"],["G♭-10","C♯11","A4","D♭-8"],["G♭-10","C♭-11","B7","D♭-8","F-2"],["G1","F-2"],["D3","D3","E6","B7","F-2"],["C♭-11","E♭-5"],["D3","B7","G1"],["B♭-4","A4"],["A♭-7","E6","C♯11","C♯11","F-2"],["A♭-7","E6","G♭-10","D♭-8"],["A♭-7","A♭-7","D♭-8"],["B♭-4","F♯9"],["D3","G♭-10","B♭-4","D♭-8","E♭-5"],["A♭-7","C♯11"],["B7","B♭-4","E♭-5","F-2"],["G♭-10","C♭-11","D♭-8","G1","F-2"],["C♭-11","C♭-11","C0"],["D3","A♭-7","F♯9","F-2"],["G♭-10","C0","C♯11","F-2"],["A♭-7","G♭-10","G♭-10","B7"],["D3","A♭-7","E♭-5","F♯9"],["D♭-8","D♭-8","A4","E♭-5","G1"],["E6","G1","E♭-5","F-2"],["D3","E6","A4","F♯9","F♯9"],["A4","D♭-8"],["A♭-7","C0","E♭-5"],["C♭-11","B♭-4","C0","C♯11"],["B7","C♭-11","C0","D♭-8"],["E6","C♭-11","C♯11","G1","F♯9"],["G♭-10","C0","E♭-5","F-2"],["D3","G♭-10","G♭-10","C0","E♭-5"],["B7","B7","B♭-4","E♭-5","G1"],["D3","G♭-10"],["E6","G♭-10","C♭-11","C♭-11","C♯11"],["D3","G1","F♯9"],["C♭-11","B♭-4","C♯11","D♭-8","G1"],["A♭-7","B♭-4","A4","A4"],["C♯11","G1"],["A♭-7","C0"],["G♭-10","F-2"],["A♭-7","G♭-10","B♭-4","C0","F♯9"],["G♭-10","B♭-4","C♯11","D♭-8","F♯9"],["E6","G♭-10","B7","B♭-4"],["C♯11","A4","F♯9","F♯9"],["E♭-5","F-2"],["A♭-7","B7","E♭-5","F-2"],["D3","D3","B♭-4","C♯11"],["G♭-10","C♭-11","C♯11","E♭-5","F♯9"],["E6","C♭-11"],["D3","D♭-8","A4"],["B7","C0"],["E6","B7","B♭-4","G1","F♯9"],["D3","D3","G♭-10","C♯11"],["G♭-10","C♯11","D♭-8","F♯9"],["C♭-11","E♭-5","E♭-5"],["A♭-7","G♭-10","G1","F♯9"],["G♭-10","D♭-8","D♭-8","E♭-5","F♯9"],["D3","B7","F♯9","F♯9"],["D3","A♭-7","A♭-7","B7","C♭-11"],["D3","C♯11","F♯9"],["A♭-7","E6","C♭-11","A4","G1"],["A♭-7","B♭-4","D♭-8","F♯9"],["C♭-11","F♯9","F♯9"],["F♯9","F♯9"],["B♭-4","B♭-4","A4","A4"],["B7","B7","B7","C0"],["C♭-11","E♭-5"],["D3","C♭-11","B♭-4","B♭-4"],["C♭-11","B♭-4","A4","D♭-8"],["B7","B7","B7","C♭-11","E♭-5"],["D3","A♭-7","C0"],["B7","B♭-4","D♭-8"],["C0","D♭-8","E♭-5","F-2"],["A♭-7","B7","C0","A4","F-2"],["C♭-11","C♭-11","C♯11","A4","D♭-8"],["A♭-7","G♭-10","B♭-4","B♭-4","C♯11"],["D3","B7","A4","G1","E♭-5"],["E6","C♯11"],["A♭-7","B7","B♭-4","C♯11","F-2"],["A♭-7","C♯11","D♭-8","A4"],["C♯11","E♭-5","F♯9","F♯9"],["D3","C♭-11","G1","G1"],["G♭-10","F♯9"],["E6","B7","C♯11","E♭-5","F♯9"],["A♭-7","E6","C♭-11","D♭-8","F-2"],["A♭-7","A♭-7","A♭-7","G1","F-2"],["G♭-10","C♯11"],["G♭-10","B7","C0","E♭-5"],["E6","E6","D♭-8","G1"],["D3","C♭-11"],["G♭-10","G♭-10","B7","G1"],["E6","B7","B♭-4","B♭-4","E♭-5"],["C0","B♭-4","A4","G1"],["D3","D3","D3","E6"],["A♭-7","A4","F♯9","F-2"],["C♭-11","B♭-4","D♭-8"],["G♭-10","G1","G1"],["D3","D3","A♭-7","F♯9"],["D3","C♭-11","D♭-8","A4","A4"],["A♭-7","G1"],["E6","E6","B7"],["C♭-11","B♭-4","C♯11"],["A♭-7","E♭-5","F♯9"],["C0","A4","E♭-5","G1","G1"],["E6","C♭-11","C0","D♭-8","D♭-8"],["E6","E♭-5","F♯9"],["A♭-7","C♭-11","B7","D♭-8"],["B7","D♭-8","E♭-5"],["E6","C♭-11","E♭-5","F♯9"],["G♭-10","C♯11"],["E6","B7","D♭-8","E♭-5"],["A♭-7","G♭-10","C♯11","D♭-8","F-2"],["D♭-8","A4","A4","A4"],["B7","C♭-11","B♭-4","A4"],["D3","C♭-11","F-2"],["E6","B♭-4","C0","C♯11"],["C♭-11","F-2"],["A♭-7","G♭-10","D♭-8","G1"]]},{"accuracy":1.764705882352941e-2,"chordLabels":["AM","Bo7","DM","G♭M","Bo","FMm7","A♭Mm7","AM","G♭M","A♭M","DM","C♭M","A♭+","Fm","DM","GM","AM","B♭Mm7","D♭M","G♭M","DM","C♭M","CM","GM","Go","BM","F♯Mm7","Gm","GM","A♭MM7","E♭Mm7","DMm7","E♭M","B♭M","Ao7","BM","C♭M","AM","FM","GM","BMm7","G♭M","CM","E♭M","Do7","Bo7","Do7","C♭M","F♯Ger","CM","Bm","F♯M","BM","F♯o7","Eo7","FMm7","F♯%7","F♯o","B♭M","DMm7","B♭M","DM","DM","Ao7","EM","E♭m","FM","DM","GM","A♭Mm7","DMm7","AM","A♭M","CM","GM","Ao","CM","E♭M","C♯Ger","Ao7","A♭Mm7","DMm7","Bo7","GM","Am","GM","GMm7","DM","Bo","G♭M","Em","D♭M","Fm","GM","FM","FM","Eo7","A♭M","F♯Mm7","Ao7","F♯o7","AM","B♭Mm7","GM","A♭M","A♭m","BM","E♭M","Fm","BM","C♭M","FM","A♭M","Gm","Bm","E♭M","E♭mm7","C♭M","FM","CM","Ao","C♭M","DM","C♭M","B♭m","B♭M","D♭Mm7","DM","GM","FM","Dm","GM","Gm","DM","Gm","E♭M","Eo","G♭M","AMm7","GMm7","Bo7","DM","B♭M","Go","D♭M","C♭M","DM","C♯o7","F♯o7","GM","AM","Ao7","DM","Do7","G♭M","C♭M","Ao7","Do7","GM","GM","C♯o7","D♭Mm7","B♭M","Fo","Eo","FM","D♭M","CM","EM","C♭M"],"likelihood":-15.043059624224334,"reruns":1,"runTime":7.8397e-5,"slices":[["A♭-7","B7","C♯11","A4"],["A♭-7","D3","B7","B♭-4","F♯9"],["D♭-8","F♯9"],["G♭-10","A4","D♭-8"],["B7","C♯11","F-2","F-2"],["A4","E♭-5"],["A♭-7","D3","G♭-10"],["A♭-7","C♯11"],["G♭-10","D♭-8","F-2"],["C♭-11","C0"],["B♭-4","A4","F♯9"],["G♭-10","E♭-5"],["A♭-7","E6","E6","C♭-11"],["A♭-7","C0","G1","F♯9","F-2"],["B♭-4","A4","F♯9"],["D3","C♭-11","B7","B7","E♭-5"],["A4","A4"],["A♭-7","B♭-4","A4","F♯9"],["D♭-8","F-2"],["B♭-4","D♭-8"],["G♭-10","F♯9"],["G♭-10","G♭-10","C♭-11"],["B7","C0","C0"],["D3","A4","G1"],["D♭-8","D♭-8","A4","G1"],["B7","C♯11","F♯9"],["C♭-11","C♯11","F♯9"],["D3","B♭-4","D♭-8","G1","G1"],["D3","B7","E♭-5"],["A♭-7","C♭-11","C0","G1","G1"],["D♭-8","E♭-5"],["D3","C0"],["B♭-4","G1"],["D3","B♭-4"],["G♭-10","G♭-10","C♯11"],["B7","B7"],["G♭-10","B7","C♭-11"],["E6","C♯11"],["C0","C0","A4"],["C♭-11","G1","F♯9"],["B7","A4"],["G♭-10","G♭-10","B♭-4","D♭-8"],["E6","G1"],["B♭-4","E♭-5"],["C♭-11","A4"],["A♭-7","B7","F♯9"],["D3","E6","C♭-11","C♭-11","B♭-4"],["C♭-11","C♭-11"],["A♭-7","D♭-8","G1","F♯9","F♯9"],["D3","C♭-11","B7","C0","C♯11"],["G♭-10","B7","C♯11","F-2"],["G♭-10","C♯11","F♯9"],["B7","F♯9"],["E♭-5","F♯9"],["B7","D♭-8"],["C♭-11","E♭-5","F♯9","F-2"],["E6","C♭-11","C0","F♯9"],["A♭-7","C♯11","A4","G1","F♯9"],["D3","D3","G♭-10"],["D3","C0","A4"],["D3","D3","G♭-10","A4","F-2"],["D3","A4"],["A♭-7","G1","F♯9","F♯9"],["G♭-10","C♯11","E♭-5","F-2"],["E6","B7","C♯11"],["G♭-10","E♭-5","E♭-5"],["C0","A4"],["E6","G1","F♯9","F♯9","F♯9"],["B7","G1"],["A♭-7","A♭-7","G♭-10"],["C0","F♯9"],["A♭-7","C♯11"],["A♭-7","D♭-8","G1"],["E6","G1"],["E6","G♭-10","B7","A4","G1"],["G♭-10","E6","E♭-5","F♯9"],["E6","G1"],["G♭-10","B♭-4","G1"],["C♯11","C♯11","D♭-8","E♭-5"],["G♭-10","C♯11","A4"],["G♭-10","C♭-11","C0","G1"],["D3","C0","F♯9"],["A♭-7","B7"],["B7","E♭-5"],["E6","C0","A4"],["D3","B♭-4","E♭-5","G1","F♯9"],["E6","B7","F-2","F-2"],["D3","C♯11","E♭-5"],["B7","B7","C♯11","E♭-5","F-2"],["G♭-10","D♭-8","G1"],["E6","B7","B7","B♭-4","C♯11"],["A♭-7","D♭-8"],["A♭-7","A♭-7","C0","G1","F-2"],["G♭-10","B7","G1"],["E6","F-2"],["A4","G1","F-2"],["E6","D♭-8"],["A♭-7","A4","E♭-5"],["A♭-7","E6","F♯9"],["E6","G♭-10","C♯11","E♭-5"],["E6","E♭-5","F♯9"],["C♯11","F-2"],["D3","A♭-7","A♭-7","C♯11"],["A♭-7","B7","G1","F♯9"],["A♭-7","C0"],["A♭-7","C♭-11","B7"],["B7","F♯9"],["A♭-7","G♭-10","E♭-5","G1","F-2"],["A♭-7","A♭-7","E♭-5","F♯9","F-2"],["E6","G♭-10","B7","F♯9"],["C♭-11","C♭-11","C0"],["A♭-7","C0","A4","G1"],["A♭-7","C♯11","E♭-5"],["D3","D3","B♭-4","D♭-8","G1"],["B7","F♯9","F-2"],["D3","G♭-10","E♭-5"],["G♭-10","G♭-10","C♯11","D♭-8","E♭-5"],["G♭-10","C♭-11","C♭-11","B♭-4"],["C0","B♭-4","A4","D♭-8"],["E6","G♭-10","C0","G1","G1"],["A♭-7","B♭-4","C♯11","A4","E♭-5"],["C♭-11","B♭-4","E♭-5"],["D3","C♯11"],["C♭-11","E♭-5"],["B♭-4","C♯11","D♭-8"],["D3","D3","G♭-10","G1","F-2"],["D3","C♭-11","D♭-8"],["D3","E6","B7","A4","F♯9"],["E6","B7","E♭-5","F♯9","F-2"],["A♭-7","E6","D♭-8","F♯9","F-2"],["A♭-7","D3","A4","G1"],["B7","C♭-11","G1"],["B♭-4","A4","G1"],["D3","E♭-5","F♯9"],["D3","C♭-11","A4","D♭-8","G1"],["B7","B♭-4","E♭-5"],["G♭-10","E6","C♯11","G1","F-2"],["G♭-10","G♭-10","F♯9","F-2"],["G♭-10","C♯11","C♯11","A4","G1"],["B7","F-2"],["B7","D♭-8","E♭-5","F♯9","F-2"],["D3","G♭-10","C♯11","A4"],["D3","F-2"],["D3","B♭-4","D♭-8","D♭-8","G1"],["A♭-7","C0","D♭-8","F-2"],["E6","C♭-11","C♭-11"],["D3","A4","A4"],["B♭-4","C♯11"],["A♭-7","E♭-5","F♯9"],["D3","B7"],["E6","C♯11","F-2"],["G♭-10","C0","B♭-4","A4","G1"],["D3","C♯11","D♭-8","E♭-5","F♯9"],["A♭-7","C♭-11","F♯9"],["B♭-4","D♭-8"],["G♭-10","C♭-11","B♭-4","E♭-5"],["G♭-10","B♭-4","C0","A4"],["D3","A♭-7","C♭-11","C0"],["G1","F♯9"],["D3","D3","E6","E♭-5"],["A♭-7","E6","B♭-4","C♯11"],["C♭-11","C♭-11","A4","D♭-8"],["G♭-10","F♯9","F-2"],["G♭-10","C♭-11","C0","F-2","F-2"],["E6","B♭-4","G1","F-2"],["A♭-7","B♭-4","C0","A4","F-2"],["D3","A♭-7","D♭-8"],["B7","C♭-11","C0"],["E6","B7","B7"],["C♭-11","E♭-5"]]}]}